particle_sdk/__init__.py
particle_sdk/_base_client.py
particle_sdk/_client.py
particle_sdk/_compat.py
particle_sdk/_constants.py
particle_sdk/_exceptions.py
particle_sdk/_files.py
particle_sdk/_models.py
particle_sdk/_qs.py
particle_sdk/_resource.py
particle_sdk/_response.py
particle_sdk/_streaming.py
particle_sdk/_types.py
particle_sdk/_version.py
particle_sdk/py.typed
particle_sdk/_utils/__init__.py
particle_sdk/_utils/_logs.py
particle_sdk/_utils/_proxy.py
particle_sdk/_utils/_reflection.py
particle_sdk/_utils/_resources_proxy.py
particle_sdk/_utils/_streams.py
particle_sdk/_utils/_sync.py
particle_sdk/_utils/_transform.py
particle_sdk/_utils/_typing.py
particle_sdk/_utils/_utils.py
particle_sdk/lib/.keep
particle_sdk/resources/__init__.py
particle_sdk/resources/auth.py
particle_sdk/resources/deltas.py
particle_sdk/resources/documents.py
particle_sdk/resources/files.py
particle_sdk/resources/patients.py
particle_sdk/resources/queries.py
particle_sdk/resources/projects/__init__.py
particle_sdk/resources/projects/batches.py
particle_sdk/resources/projects/projects.py
particle_sdk/types/__init__.py
particle_sdk/types/auth_generate_token_response.py
particle_sdk/types/delta_collect_flat_datasets_params.py
particle_sdk/types/delta_collect_flat_datasets_response.py
particle_sdk/types/delta_retrieve_resource_response.py
particle_sdk/types/delta_submit_params.py
particle_sdk/types/delta_submit_response.py
particle_sdk/types/document.py
particle_sdk/types/document_get_patient_documents_response.py
particle_sdk/types/document_submit_params.py
particle_sdk/types/patient.py
particle_sdk/types/patient_list_params.py
particle_sdk/types/patient_list_response.py
particle_sdk/types/patient_search_params.py
particle_sdk/types/patient_search_response.py
particle_sdk/types/patient_submit_params.py
particle_sdk/types/query.py
particle_sdk/types/query_create_params.py
particle_sdk/types/query_list_response.py
particle_sdk/types/response_message.py
particle_sdk-0.1.0a7.dist-info/METADATA
particle_sdk-0.1.0a7.dist-info/WHEEL
particle_sdk-0.1.0a7.dist-info/licenses/LICENSE
particle_sdk-0.1.0a7.dist-info/RECORD
